fashion_words/__init__.py
fashion_words/categories.json
fashion_words/words.py
fashion_words-0.3.dist-info/METADATA
fashion_words-0.3.dist-info/WHEEL
fashion_words-0.3.dist-info/top_level.txt
fashion_words-0.3.dist-info/RECORD
