Metadata-Version: 2.1
Name: fashion_words
Version: 0.3
Summary: Um pacote de palavras relacionadas à moda para NLP
Author: Melissa Albuquerque
Requires-Python: >=3.6
